[
    {
        "field_name": "wemwbs_1",
        "form_name": "wemwbs",
        "section_header": "How well does each of the following statements describe your behaviours/feelings today?",
        "field_type": "radio",
        "field_label": "I felt optimistic about the future",
        "select_choices_or_calculations": [
            {
                "code": "1",
                "label": "None of the time"
            },
            {
                "code": "2",
                "label": "Rarely"
            },
            {
                "code": "3",
                "label": "Some of the time"
            },
            {
                "code": "4",
                "label": "Often"
            },
            {
                "code": "5",
                "label": "All of the time"
            }
        ],
        "field_note": "",
        "text_validation_type_or_show_slider_number": "",
        "text_validation_min": "",
        "text_validation_max": "",
        "identifier": "",
        "branching_logic": "",
        "required_field": "y",
        "custom_alignment": "",
        "question_number": "",
        "matrix_group_name": "wemwbs",
        "matrix_ranking": "",
        "field_annotation": "",
        "evaluated_logic": ""
    },
    {
        "field_name": "wemwbs_2",
        "form_name": "wemwbs",
        "section_header": "",
        "field_type": "radio",
        "field_label": "I felt useful",
        "select_choices_or_calculations": [
            {
                "code": "1",
                "label": "None of the time"
            },
            {
                "code": "2",
                "label": "Rarely"
            },
            {
                "code": "3",
                "label": "Some of the time"
            },
            {
                "code": "4",
                "label": "Often"
            },
            {
                "code": "5",
                "label": "All of the time"
            }
        ],
        "field_note": "",
        "text_validation_type_or_show_slider_number": "",
        "text_validation_min": "",
        "text_validation_max": "",
        "identifier": "",
        "branching_logic": "",
        "required_field": "y",
        "custom_alignment": "",
        "question_number": "",
        "matrix_group_name": "wemwbs",
        "matrix_ranking": "",
        "field_annotation": "",
        "evaluated_logic": ""
    },
    {
        "field_name": "wemwbs_3",
        "form_name": "wemwbs",
        "section_header": "",
        "field_type": "radio",
        "field_label": "I felt close to other people",
        "select_choices_or_calculations": [
            {
                "code": "1",
                "label": "None of the time"
            },
            {
                "code": "2",
                "label": "Rarely"
            },
            {
                "code": "3",
                "label": "Some of the time"
            },
            {
                "code": "4",
                "label": "Often"
            },
            {
                "code": "5",
                "label": "All of the time"
            }
        ],
        "field_note": "",
        "text_validation_type_or_show_slider_number": "",
        "text_validation_min": "",
        "text_validation_max": "",
        "identifier": "",
        "branching_logic": "",
        "required_field": "y",
        "custom_alignment": "",
        "question_number": "",
        "matrix_group_name": "wemwbs",
        "matrix_ranking": "",
        "field_annotation": "",
        "evaluated_logic": ""
    },
    {
        "field_name": "wemwbs_4",
        "form_name": "wemwbs",
        "section_header": "",
        "field_type": "radio",
        "field_label": "I was able to make up my own mind about things",
        "select_choices_or_calculations": [
            {
                "code": "1",
                "label": "None of the time"
            },
            {
                "code": "2",
                "label": "Rarely"
            },
            {
                "code": "3",
                "label": "Some of the time"
            },
            {
                "code": "4",
                "label": "Often"
            },
            {
                "code": "5",
                "label": "All of the time"
            }
        ],
        "field_note": "",
        "text_validation_type_or_show_slider_number": "",
        "text_validation_min": "",
        "text_validation_max": "",
        "identifier": "",
        "branching_logic": "",
        "required_field": "y",
        "custom_alignment": "",
        "question_number": "",
        "matrix_group_name": "wemwbs",
        "matrix_ranking": "",
        "field_annotation": "",
        "evaluated_logic": ""
    },
    {
        "field_name": "wemwbs_5",
        "form_name": "wemwbs",
        "section_header": "",
        "field_type": "radio",
        "field_label": "I felt good about myself",
        "select_choices_or_calculations": [
            {
                "code": "1",
                "label": "None of the time"
            },
            {
                "code": "2",
                "label": "Rarely"
            },
            {
                "code": "3",
                "label": "Some of the time"
            },
            {
                "code": "4",
                "label": "Often"
            },
            {
                "code": "5",
                "label": "All of the time"
            }
        ],
        "field_note": "",
        "text_validation_type_or_show_slider_number": "",
        "text_validation_min": "",
        "text_validation_max": "",
        "identifier": "",
        "branching_logic": "",
        "required_field": "y",
        "custom_alignment": "",
        "question_number": "",
        "matrix_group_name": "wemwbs",
        "matrix_ranking": "",
        "field_annotation": "",
        "evaluated_logic": ""
    },
    {
        "field_name": "wemwbs_6",
        "form_name": "wemwbs",
        "section_header": "",
        "field_type": "radio",
        "field_label": "I felt loved",
        "select_choices_or_calculations": [
            {
                "code": "1",
                "label": "None of the time"
            },
            {
                "code": "2",
                "label": "Rarely"
            },
            {
                "code": "3",
                "label": "Some of the time"
            },
            {
                "code": "4",
                "label": "Often"
            },
            {
                "code": "5",
                "label": "All of the time"
            }
        ],
        "field_note": "",
        "text_validation_type_or_show_slider_number": "",
        "text_validation_min": "",
        "text_validation_max": "",
        "identifier": "",
        "branching_logic": "",
        "required_field": "y",
        "custom_alignment": "",
        "question_number": "",
        "matrix_group_name": "wemwbs",
        "matrix_ranking": "",
        "field_annotation": "",
        "evaluated_logic": ""
    }
]